changepacks/__main__.py
changepacks-0.2.15.data/scripts/changepacks
changepacks-0.2.15.dist-info/METADATA
changepacks-0.2.15.dist-info/WHEEL
changepacks-0.2.15.dist-info/RECORD
